waveradio/__init__.py
waveradio/app.py
waveradio/conf.py
waveradio/main.py
waveradio_0.4-0.2.data/scripts/wave
waveradio_0.4-0.2.dist-info/METADATA
waveradio_0.4-0.2.dist-info/WHEEL
waveradio_0.4-0.2.dist-info/top_level.txt
waveradio_0.4-0.2.dist-info/RECORD
