Metadata-Version: 2.1
Name: waveradio-0.4
Version: 0.2
Summary: Serius Ini Deskripsi
Home-page: https://malikamovieonline.web.app
Author: Muhammad Al Fajri
Author-email: fajrim228@gmail.com
License: P.O number 3112, Padang Panjang License
Platform: UNKNOWN
Requires-Dist: waveradio-0.3
